{
  "name": "sheet-stack-demo",
  "files": [
    {
      "name": "sheet-stack-demo.tsx",
      "content": "\"use client\"\n\nimport { Button, Sheet } from \"ui\"\n\nexport default function SheetStackDemo() {\n  return (\n    <Sheet>\n      <Button appearance=\"outline\">Stack</Button>\n      <Sheet.Content isStack={false}>\n        <Sheet.Header>\n          <Sheet.Title>Not Stacked</Sheet.Title>\n          <Sheet.Description>This sheet is not stacked.</Sheet.Description>\n        </Sheet.Header>\n        <Sheet.Footer>\n          <Sheet.Close>Cancel</Sheet.Close>\n          <Button intent=\"primary\">Save Changes</Button>\n        </Sheet.Footer>\n      </Sheet.Content>\n    </Sheet>\n  )\n}\n"
    }
  ],
  "type": "components:demo",
  "componentPath": "components/docs/overlays/sheet/sheet-stack-demo.tsx"
}