{
  "name": "app-sidebar-nav",
  "files": [
    {
      "name": "app-sidebar-nav.tsx",
      "content": "\"use client\"\n\nimport { IconCommandRegular, IconDashboard, IconHeadphones, IconLogout, IconMic, IconSettings } from \"justd-icons\"\nimport { Avatar, Button, Menu, SearchField, SidebarNav, SidebarTrigger } from \"ui\"\n\nexport default function AppSidebarNav() {\n  return (\n    <SidebarNav className=\"flex justify-between border-b-0 sm:mt-2\">\n      <SidebarTrigger />\n      <div className=\"flex gap-x-2 items-center mx-auto sm:min-w-120\">\n        <SearchField className=\"w-full\" />\n        <Button size=\"square-petite\" className=\"size-10\" appearance=\"plain\">\n          <IconMic />\n        </Button>\n      </div>\n      <div>\n        <Menu>\n          <Menu.Trigger aria-label=\"Open Menu\">\n            <Avatar alt=\"cobain\" src=\"/images/avatar/cobain.jpg\" />\n          </Menu.Trigger>\n          <Menu.Content placement=\"bottom\" className=\"sm:min-w-56\">\n            <Menu.Section>\n              <Menu.Header separator>\n                <span className=\"block\">Kurt Cobain</span>\n                <span className=\"font-normal text-muted-fg\">@cobain</span>\n              </Menu.Header>\n            </Menu.Section>\n\n            <Menu.Item href=\"#dashboard\">\n              <IconDashboard />\n              Dashboard\n            </Menu.Item>\n            <Menu.Item href=\"#settings\">\n              <IconSettings />\n              Settings\n            </Menu.Item>\n            <Menu.Separator />\n            <Menu.Item>\n              <IconCommandRegular />\n              Command Menu\n            </Menu.Item>\n            <Menu.Separator />\n            <Menu.Item href=\"#contact-s\">\n              <IconHeadphones />\n              Contact Support\n            </Menu.Item>\n            <Menu.Separator />\n            <Menu.Item href=\"#logout\">\n              <IconLogout />\n              Log out\n            </Menu.Item>\n          </Menu.Content>\n        </Menu>\n      </div>\n    </SidebarNav>\n  )\n}\n"
    }
  ],
  "type": "components:blocks",
  "componentPath": "app/blocks/sidebar/sidebar-19/app-sidebar-nav.tsx"
}