{
  "name": "list-box-demo",
  "files": [
    {
      "name": "list-box-demo.tsx",
      "content": "\"use client\"\n\nimport { ListBox } from \"ui\"\n\nexport default function ListBoxDemo() {\n  return (\n    <ListBox items={rockPopBands} selectionMode=\"single\" aria-label=\"Bands\">\n      {(item) => <ListBox.Item id={item.id}>{item.name}</ListBox.Item>}\n    </ListBox>\n  )\n}\n\nconst rockPopBands = [\n  { id: \"1\", name: \"Nirvana\" },\n  { id: \"2\", name: \"Radiohead\" },\n  { id: \"3\", name: \"Foo Fighters\" },\n  { id: \"4\", name: \"Arctic Monkeys\" },\n  { id: \"5\", name: \"The Strokes\" },\n]\n"
    }
  ],
  "type": "components:demo",
  "componentPath": "components/docs/collections/list-box/list-box-demo.tsx"
}