{
  "name": "menu-with-arrow-demo",
  "files": [
    {
      "name": "menu-with-arrow-demo.tsx",
      "content": "\"use client\"\n\nimport React from \"react\"\n\nimport { IconHashtag, IconHeadphones, IconLogout, IconPlus, IconSettings } from \"justd-icons\"\nimport { Avatar, Menu } from \"ui\"\n\nexport default function MenuWithArrowDemo() {\n  return (\n    <>\n      <Menu>\n        <Menu.Trigger aria-label=\"Open Menu\">\n          <Avatar className=\"size-10\" src=\"https://github.com/irsyadadl.png\" />\n        </Menu.Trigger>\n        <Menu.Content placement=\"bottom\" showArrow className=\"min-w-64\">\n          <Menu.Section>\n            <Menu.Header separator>\n              <span className=\"block\">Irsyad A. Panjaitan</span>\n              <span className=\"font-normal text-muted-fg\">@irsyadadl</span>\n            </Menu.Header>\n          </Menu.Section>\n          <Menu.Item>\n            <IconSettings />\n            Settings\n          </Menu.Item>\n          <Menu.Item href=\"#\">\n            <IconPlus />\n            Create Team\n          </Menu.Item>\n          <Menu.Item href=\"#\">\n            <IconHashtag />\n            Command Menu\n            <Menu.Keyboard keys=\"⌘K\" />\n          </Menu.Item>\n          <Menu.Separator />\n          <Menu.Item href=\"#\">\n            <IconHeadphones />\n            Contact Support\n          </Menu.Item>\n          <Menu.Separator />\n          <Menu.Item>\n            <IconLogout />\n            Log out\n          </Menu.Item>\n        </Menu.Content>\n      </Menu>\n    </>\n  )\n}\n"
    }
  ],
  "type": "components:demo",
  "componentPath": "components/docs/collections/menu/menu-with-arrow-demo.tsx"
}